tslogs/__init__.py
tslogs/__main__.py
tslogs/_version.txt
tslogs/cli.py
tslogs/data_ploting.py
tslogs/parse.py
tslogs/stats.py
tslogs/utils.py
tslogs-0.1.0.dist-info/COPYING
tslogs-0.1.0.dist-info/METADATA
tslogs-0.1.0.dist-info/WHEEL
tslogs-0.1.0.dist-info/entry_points.txt
tslogs-0.1.0.dist-info/top_level.txt
tslogs-0.1.0.dist-info/zip-safe
tslogs-0.1.0.dist-info/RECORD
