Metadata-Version: 2.1
Name: tslogs
Version: 0.1.0
Summary: ThrottleStop logs parsers and visualizer.
Home-page: https://github.com/ashutoshvarma/tslogs
Author: Ashutosh Varma
Author-email: ashutoshvarma11@live.com
License: MIT
Project-URL: Bug Tracker, https://github.com/ashutoshvarma/tslogs/issues
Keywords: throttlestop,logs,convert,parse,graph,visualizer
Platform: any
Classifier: Development Status :: 4 - Beta
Classifier: Programming Language :: Python
Classifier: Programming Language :: Python :: 3
Classifier: Programming Language :: Python :: 3.8
Classifier: Programming Language :: Python :: 3.9
Classifier: License :: OSI Approved :: MIT License
Classifier: Topic :: Software Development :: Libraries :: Python Modules
Classifier: Operating System :: OS Independent
Requires-Python: >= 3.6
Requires-Dist: matplotlib (>=3.3.2)
Requires-Dist: colorama (>=0.4.3)
Provides-Extra: all
Requires-Dist: sphinx ; extra == 'all'
Requires-Dist: codecov ; extra == 'all'
Requires-Dist: coverage ; extra == 'all'
Requires-Dist: pytest ; extra == 'all'
Requires-Dist: pytest-cov ; extra == 'all'
Requires-Dist: tox ; extra == 'all'
Provides-Extra: doc
Requires-Dist: sphinx ; extra == 'doc'
Provides-Extra: test
Requires-Dist: codecov ; extra == 'test'
Requires-Dist: coverage ; extra == 'test'
Requires-Dist: pytest ; extra == 'test'
Requires-Dist: pytest-cov ; extra == 'test'
Requires-Dist: tox ; extra == 'test'
